cloudops_commander/__init__.py
cloudops_commander/cli.py
cloudops_commander/config.py
cloudops_commander/deploy.py
cloudops_commander/iac.py
cloudops_commander/monitor.py
cloudops_commander/utils.py
tests/__init__.py
tests/test_deploy.py
tests/test_iac.py
tests/test_monitor.py
cloudops_commander-0.1.1.dist-info/LICENSE
cloudops_commander-0.1.1.dist-info/METADATA
cloudops_commander-0.1.1.dist-info/WHEEL
cloudops_commander-0.1.1.dist-info/top_level.txt
cloudops_commander-0.1.1.dist-info/RECORD
