Metadata-Version: 2.1
Name: cloudops_commander
Version: 0.1.1
Summary: A package for simplifying cloud deployments, automating CI/CD pipelines, and monitoring microservices.
Home-page: https://github.com/bluntlycoded/cloudops_commander.git
Author: Rahul Nayak
Author-email: merahulnayak@gmail.com
Classifier: Programming Language :: Python :: 3
Classifier: License :: OSI Approved :: MIT License
Classifier: Operating System :: OS Independent
Requires-Python: >=3.6
License-File: LICENSE
